<?xml version="1.0" encoding="UTF-8" ?>

<!--
 Permitted values for <Result> are - 
 
        "Win" / "Won"
        "Lose" / "Lost"
        "Draw"
        ""Tie"
        "Rain"
        "Abandonned"
        "NP"
        "NotYetPlayed"
        "Cancelled"
-->

<YearsFixtures>

<Fixture>
  <Date>Sun, 24 Apr 2016 12:00:00 UTC</Date>
  <Opposition>Stonor</Opposition>
  <Time>13:30</Time>
  <Venue>Away</Venue>
  <Result>Draw</Result>
  <HasLink/>
</Fixture>

<Fixture>
  <Date>Sun, 1 May 2016 12:00:00 UTC</Date>
  <Opposition>Bracknell</Opposition>
  <Time>14:00</Time>
  <Venue>Home</Venue>
  <Result>Draw</Result>
  <HasLink/>
</Fixture>

<Fixture>
  <Date>Sun, 8 May 2016 12:00:00 UTC</Date>
  <Opposition>Sonning</Opposition>
  <Time>14:00</Time>
  <Venue>Away</Venue>
  <Result>Lose</Result>
  <HasLink/>
</Fixture>

<Fixture>
  <Date>Sun, 15 May 2016 12:00:00 UTC</Date>
  <Opposition>Swyncombe</Opposition>
  <Time>14:00</Time>
  <Venue>Home</Venue>
  <Result>Draw</Result>
  <HasLink/>
</Fixture>

<Fixture>
  <Date>Sun, 22 May 2016 12:00:00 UTC</Date>
  <Opposition>Frieth</Opposition>
  <Time>14:00</Time>
  <Venue>Away</Venue>
  <Result>Cancelled</Result>
  <HasLink/>
</Fixture>

<Fixture>
  <Date>Sun, 29 May 2016 12:00:00 UTC</Date>
  <Opposition>Theale and Tilehurst</Opposition>
  <Time>14:00</Time>
  <Venue>Home</Venue>
  <Result>Draw</Result>
  <HasLink/>
</Fixture>

<Fixture>
  <Date>Sun, 5 Jun 2016 12:00:00 UTC</Date>
  <Opposition>Greys Green</Opposition>
  <Time>13:30</Time>
  <Venue>Away</Venue>
  <Result>NotYetPlayed</Result>
</Fixture>

<Fixture>
  <Date>Sun, 12 Jun 2016 12:00:00 UTC</Date>
  <Opposition>Littlewick Green</Opposition>
  <Time>14:00</Time>
  <Venue>Away</Venue>
  <Result>NotYetPlayed</Result>
</Fixture>

<Fixture>
  <Date>Sun, 19 Jun 2016 12:00:00 UTC</Date>
  <Opposition>Crowthorne and Crown Wood</Opposition>
  <Time>14:00</Time>
  <Venue>Home</Venue>
  <Result>NotYetPlayed</Result>
</Fixture>

<Fixture>
  <Date>Sun, 26 Jun 2016 12:00:00 UTC</Date>
  <Opposition>Ibstone</Opposition>
  <Time>14:00</Time>
  <Venue>Away</Venue>
  <Result>NotYetPlayed</Result>
</Fixture>

<Fixture>
  <Date>Sun, 3 Jul 2016 12:00:00 UTC</Date>
  <Opposition>Hurst</Opposition>
  <Time>14:00</Time>
  <Venue>Home</Venue>
  <Result>NotYetPlayed</Result>
</Fixture>

<Fixture>
  <Date>Sun, 10 Jul 2016 12:00:00 UTC</Date>
  <Opposition>Woodcote</Opposition>
  <Time>14:00</Time>
  <Venue>Away</Venue>
  <Result>NotYetPlayed</Result>
</Fixture>

<Fixture>
  <Date>Sun, 17 Jul 2016 12:00:00 UTC</Date>
  <Opposition>Fawley Village</Opposition>
  <Time>14:00</Time>
  <Venue>Away</Venue>
  <Result>NotYetPlayed</Result>
</Fixture>

<Fixture>
  <Date>Sun, 24  Jul 2016 12:00:00 UTC</Date>
  <Opposition>Warfield</Opposition>
  <Time>13:30</Time>
  <Venue>Away</Venue>
  <Result>NotYetPlayed</Result>
</Fixture>

<Fixture>
  <Date>Sun, 31 Jul 2016 12:00:00 UTC</Date>
  <Opposition>Ipsden</Opposition>
  <Time>14:00</Time>
  <Venue>Home</Venue>
  <Result>NotYetPlayed</Result>
</Fixture>

<Fixture>
  <Date>Sun, 7 Aug 2016 12:00:00 UTC</Date>
  <Opposition>Pinkneys Green</Opposition>
  <Time>14:00</Time>
  <Venue>Home</Venue>
  <Result>NotYetPlayed</Result>
</Fixture>

<Fixture>
  <Date>Sun, 14 Aug 2016 12:00:00 UTC</Date>
  <Opposition>Checkendon</Opposition>
  <Time>14:00</Time>
  <Venue>Away</Venue>
  <Result>NotYetPlayed</Result>
</Fixture>

<Fixture>
  <Date>Sun, 21 Aug 2016 12:00:00 UTC</Date>
  <Opposition>Joe Downes XI</Opposition>
  <Time>14:00</Time>
  <Venue>Home</Venue>
  <Result>NotYetPlayed</Result>
</Fixture>

<Fixture>
  <Date>Sun, 28 Aug 2016 12:00:00 UTC</Date>
  <Opposition>Failand and Portbury</Opposition>
  <Time>13:30</Time>
  <Venue>Tour</Venue>
  <Result>NotYetPlayed</Result>
</Fixture>

<Fixture>
  <Date>Mon, 29 Aug 2016 12:00:00 UTC</Date>
  <Opposition>Cleeve</Opposition>
  <Time>14:00</Time>
  <Venue>Tour</Venue>
  <Result>NotYetPlayed</Result>
</Fixture>

<Fixture>
  <Date>Tue, 30 Aug 2016 12:00:00 UTC</Date>
  <Opposition>Harptree</Opposition>
  <Time>14:00</Time>
  <Venue>Tour</Venue>
  <Result>NotYetPlayed</Result>
</Fixture>

<Fixture>
  <Date>Sun, 4 Sep 2016 12:00:00 UTC</Date>
  <Opposition>Farley Hill</Opposition>
  <Time>13:00</Time>
  <Venue>Home</Venue>
  <Result>NotYetPlayed</Result>
</Fixture>

<Fixture>
  <Date>Sun, 11 Sep 2016 12:00:00 UTC</Date>
  <Opposition>Reading Lawyers</Opposition>
  <Time>13:00</Time>
  <Venue>Home</Venue>
  <Result>NotYetPlayed</Result>
</Fixture>

<Fixture>
  <Date>Sun, 18 Sep 2016 12:00:00 UTC</Date>
  <Opposition>Binfield</Opposition>
  <Time>13:00</Time>
  <Venue>Away</Venue>
  <Result>NotYetPlayed</Result>
</Fixture>

<Fixture>
  <Date>Sun, 25 Sep 2016 12:00:00 UTC</Date>
  <Opposition>TBA</Opposition>
  <Time>13:00</Time>
  <Venue>Away</Venue>
  <Result>NotYetPlayed</Result>
</Fixture>

</YearsFixtures>

