<?xml version="1.0" encoding="UTF-8" ?>
<!-- Generated on Thu Apr 22 19:26:01 UTC+0100 2010 -->
<CricketMatch oppo="Emmer Green" date="Sun Aug 24 00:00:00 UTC+0100 1975">
  <MatchReport/><CountsToStats/>
  <Innings batting="Emmer Green">
    <Batsman name="Jones">
      <HowOut how="Caught Stan Coates"/>
      <Bowler name="Martin Grugeon"/>
      <Runs value="18"/>
    </Batsman>
    <Batsman name="Glossop">
      <HowOut how="Bowled"/>
      <Bowler name="Martin Grugeon"/>
      <Runs value="15"/>
    </Batsman>
    <Batsman name="Shoesmith">
      <HowOut how="Stumped"/>
      <Bowler name="Matthew Fort"/>
      <Runs value="36"/>
    </Batsman>
    <Batsman name="Bowes">
      <HowOut how="Caught Stan Coates"/>
      <Bowler name="Martin Grugeon"/>
      <Runs value="6"/>
    </Batsman>
    <Batsman name="Malkin">
      <HowOut how="Caught Stan Coates"/>
      <Bowler name="Matthew Fort"/>
      <Runs value="3"/>
    </Batsman>
    <Batsman name="Gurney">
      <HowOut how="Caught J Telfer"/>
      <Bowler name="Matthew Fort"/>
      <Runs value="5"/>
    </Batsman>
    <Batsman name="West">
      <HowOut how="Not Out"/>
      <Runs value="13"/>
    </Batsman>
    <Batsman name="Gimlett">
      <HowOut how="Bowled"/>
      <Bowler name="Martin Grugeon"/>
      <Runs value="1"/>
    </Batsman>
    <Batsman name="Hobbs">
      <HowOut how="Caught Stan Coates"/>
      <Bowler name="Martin Grugeon"/>
      <Runs value="18"/>
    </Batsman>
    <Batsman name="Carp">
      <HowOut how="Not Out"/>
      <Runs value="0"/>
    </Batsman>
    <Batsman name="Spackman"/>
    <Extras value="15"/>
    <FallOfWicket batsman="1" score="45"/>
    <FallOfWicket batsman="2" score="55"/>
    <FallOfWicket batsman="4" score="65"/>
    <FallOfWicket batsman="5" score="87"/>
    <FallOfWicket batsman="3" score="96"/>
    <FallOfWicket batsman="6" score="97"/>
    <FallOfWicket batsman="8" score="99"/>
    <FallOfWicket batsman="9" score="129"/>
    <BowlerSummary name="Tom Fort" overs="6" maidens="3" runs="9" wickets="0"/>
    <BowlerSummary name="Martin Grugeon" overs="17" maidens="2" runs="51" wickets="5"/>
    <BowlerSummary name="J Telfer" overs="6" maidens="1" runs="26" wickets="0"/>
    <BowlerSummary name="Matthew Fort" overs="5" maidens="0" runs="30" wickets="3"/>
  </Innings>
  <Innings batting="Twyford">
    <Batsman name="Stan Coates">
      <HowOut how="Caught &amp; Bowled"/>
      <Bowler name="Hobbs"/>
      <Runs value="21"/>
    </Batsman>
    <Batsman name="Tom Fort">
      <HowOut how="Caught"/>
      <Bowler name="Spackman"/>
      <Runs value="77"/>
    </Batsman>
    <Batsman name="Martin Grugeon">
      <HowOut how="Caught"/>
      <Bowler name="Spackman"/>
      <Runs value="6"/>
    </Batsman>
    <Batsman name="J Telfer">
      <HowOut how="Run Out"/>
      <Runs value="3"/>
    </Batsman>
    <Batsman name="Paul Woodford">
      <HowOut how="Caught"/>
      <Bowler name="Spackman"/>
      <Runs value="3"/>
    </Batsman>
    <Batsman name="George West">
      <HowOut how="Bowled"/>
      <Bowler name="Spackman"/>
      <Runs value="14"/>
    </Batsman>
    <Batsman name="Matthew Fort">
      <HowOut how="Not Out"/>
      <Runs value="2"/>
    </Batsman>
    <Batsman name="Barry Thomas">
      <HowOut how="Not Out"/>
      <Runs value="0"/>
    </Batsman>
    <Batsman name="A Seymour"/>
    <Batsman name="Chris Telfer"/>
    <Extras value="5"/>
    <FallOfWicket batsman="1" score="54"/>
    <FallOfWicket batsman="3" score="72"/>
    <FallOfWicket batsman="4" score="85"/>
    <FallOfWicket batsman="5" score="99"/>
    <FallOfWicket batsman="2" score="129"/>
    <FallOfWicket batsman="6" score="129"/>
    <BowlerSummary name="Hobbs" overs="17.1" maidens="2" runs="57" wickets="1"/>
    <BowlerSummary name="Spackman" overs="13" maidens="1" runs="53" wickets="4"/>
    <BowlerSummary name="Glossop" overs="4" maidens="1" runs="16" wickets="0"/>
  </Innings>
</CricketMatch>

