<?xml version="1.0" encoding="utf-8"?>
<!--Generated on Sat Jun 16 2018 23:04:52 +01:00 (BST)-->
<!--Result = Draw-->
<!--XMLFilename = 2018/june_2nd_earley.xml-->
<CricketMatch oppo="Earley" date="Sat Jun 02 2018 13:00:00 +01:00 (BST)" matchType="League" team="1st XI" playCricketId="3286007">
  <MatchReport/>
  <CountsToStats/>
  <Innings batting="Twyford">
    <Batsman name="Robin Thompson">
      <HowOut how="Not Out"/>
      <Runs value="94"/>
    </Batsman>
    <Batsman name="Adam Henley">
      <HowOut how="Caught Gary Shacklady"/>
      <Bowler name="Dave Mapes"/>
      <Runs value="0"/>
    </Batsman>
    <Batsman name="Mark Higgins">
      <HowOut how="Caught Owen Bye"/>
      <Bowler name="Prasad Gore"/>
      <Runs value="20"/>
    </Batsman>
    <Batsman name="Shiva Nagam" captain="1">
      <HowOut how="LBW"/>
      <Bowler name="Sean Vis"/>
      <Runs value="58"/>
    </Batsman>
    <Batsman name="Marc Teal">
      <HowOut how="Caught Sean Vis"/>
      <Bowler name="Mo Shamoon"/>
      <Runs value="14"/>
    </Batsman>
    <Batsman name="Naresh Konduru">
      <HowOut how="Caught Tom Kernoghan"/>
      <Bowler name="Mo Shamoon"/>
      <Runs value="15"/>
    </Batsman>
    <Batsman name="Kiran Juluri">
      <HowOut how="Caught Ollie Johnson"/>
      <Bowler name="Mo Shamoon"/>
      <Runs value="2"/>
    </Batsman>
    <Batsman name="Bharani Billapati">
      <HowOut how="Not Out"/>
      <Runs value="23"/>
    </Batsman>
    <Batsman name="Chandra Cherukuri">
      <HowOut how="Did Not Bat"/>
      <Runs value="0"/>
    </Batsman>
    <Batsman name="Gopi Perumal">
      <HowOut how="Did Not Bat"/>
      <Runs value="0"/>
    </Batsman>
    <Batsman name="Ian Rogers" keeper="1">
      <HowOut how="Did Not Bat"/>
      <Runs value="0"/>
    </Batsman>
    <Extras value="23"/>
    <BowlerSummary name="Steven Mapes" overs="8" maidens="2" runs="16" wickets="0"/>
    <BowlerSummary name="Dave Mapes" overs="8" maidens="4" runs="10" wickets="1"/>
    <BowlerSummary name="Sean Vis" overs="8" maidens="0" runs="52" wickets="1"/>
    <BowlerSummary name="Prasad Gore" overs="12" maidens="1" runs="69" wickets="1"/>
    <BowlerSummary name="Gary Shacklady" overs="3" maidens="0" runs="39" wickets="0"/>
    <BowlerSummary name="Mo Shamoon" overs="6" maidens="0" runs="48" wickets="3"/>
  </Innings>
  <Innings batting="Earley">
    <Batsman name="Owen Bye">
      <HowOut how="Caught Robin Thompson"/>
      <Bowler name="Robin Thompson"/>
      <Runs value="28"/>
    </Batsman>
    <Batsman name="Gary Shacklady" captain="1">
      <HowOut how="Caught Shiva Nagam"/>
      <Bowler name="Robin Thompson"/>
      <Runs value="21"/>
    </Batsman>
    <Batsman name="Umer Malik">
      <HowOut how="LBW"/>
      <Bowler name="Kiran Juluri"/>
      <Runs value="0"/>
    </Batsman>
    <Batsman name="Ollie Johnson" keeper="1">
      <HowOut how="Bowled"/>
      <Bowler name="Shiva Nagam"/>
      <Runs value="42"/>
    </Batsman>
    <Batsman name="Tom Kernoghan">
      <HowOut how="Bowled"/>
      <Bowler name="Kiran Juluri"/>
      <Runs value="0"/>
    </Batsman>
    <Batsman name="Susan Thapa">
      <HowOut how="Run Out Mark Higgins"/>
      <Runs value="8"/>
    </Batsman>
    <Batsman name="Sean Vis">
      <HowOut how="Caught Robin Thompson"/>
      <Bowler name="Marc Teal"/>
      <Runs value="10"/>
    </Batsman>
    <Batsman name="Prasad Gore">
      <HowOut how="LBW"/>
      <Bowler name="Robin Thompson"/>
      <Runs value="4"/>
    </Batsman>
    <Batsman name="Mo Shamoon">
      <HowOut how="Not Out"/>
      <Runs value="14"/>
    </Batsman>
    <Batsman name="Dave Mapes">
      <HowOut how="Bowled"/>
      <Bowler name="Shiva Nagam"/>
      <Runs value="0"/>
    </Batsman>
    <Batsman name="Steven Mapes">
      <HowOut how="Not Out"/>
      <Runs value="0"/>
    </Batsman>
    <Extras value="32"/>
    <FallOfWicket batsman="1" score="64"/>
    <FallOfWicket batsman="2" score="64"/>
    <FallOfWicket batsman="3" score="66"/>
    <FallOfWicket batsman="5" score="69"/>
    <FallOfWicket batsman="6" score="92"/>
    <FallOfWicket batsman="7" score="110"/>
    <FallOfWicket batsman="8" score="120"/>
    <FallOfWicket batsman="4" score="138"/>
    <FallOfWicket batsman="10" score="157"/>
    <BowlerSummary name="Shiva Nagam" overs="10" maidens="1" runs="41" wickets="2"/>
    <BowlerSummary name="Bharani Billapati" overs="5" maidens="0" runs="28" wickets="0"/>
    <BowlerSummary name="Kiran Juluri" overs="9" maidens="2" runs="25" wickets="2"/>
    <BowlerSummary name="Naresh Konduru" overs="3" maidens="0" runs="11" wickets="0"/>
    <BowlerSummary name="Robin Thompson" overs="12" maidens="6" runs="13" wickets="3"/>
    <BowlerSummary name="Chandra Cherukuri" overs="2" maidens="0" runs="7" wickets="0"/>
    <BowlerSummary name="Marc Teal" overs="4" maidens="0" runs="23" wickets="1"/>
  </Innings>
</CricketMatch>
